rtl/cpu_top.v
`timescale 1ns/1ps

module cpu_top (
    input  wire clk,
    input  wire rst
);
    // Program Counter
    reg [31:0] PC;

    wire [31:0] pc_arch = PC;
    wire [31:0] pc_aligned = {pc_arch[31:2], 2'b00};
    wire [31:0] PC_plus_4 = pc_arch + 32'd4;

    // Instruction fetch
    wire [31:0] instruction;
    fetch_imem IMEM (
        .addr_word(PC[9:2]),
        .instruction(instruction)
    );

    // Decode fields
    wire [6:0] opcode   = instruction[6:0];
    wire [2:0] funct3   = instruction[14:12];
    wire [6:0] funct7   = instruction[31:25];
    wire [4:0] rd_addr  = instruction[11:7];
    wire [4:0] rs1_addr = instruction[19:15];
    wire [4:0] rs2_addr = instruction[24:20];

    // Control signals
    wire        reg_write;
    wire        alu_src;
    wire [3:0]  alu_op;
    wire        mem_read;
    wire        mem_write;
    wire [1:0]  wb_sel;
    wire        branch;
    wire [2:0]  branch_type;
    wire        auipc_flag;
    wire        lui_flag;
    wire        jal_flag;
    wire        jalr_flag;

    decoder DEC (
        .opcode(opcode),
        .funct3(funct3),
        .funct7(funct7),
        .reg_write(reg_write),
        .alu_src(alu_src),
        .alu_op(alu_op),
        .mem_read(mem_read),
        .mem_write(mem_write),
        .wb_sel(wb_sel),
        .branch(branch),
        .branch_type(branch_type),
        .auipc_flag(auipc_flag),
        .lui_flag(lui_flag),
        .jal_flag(jal_flag),
        .jalr_flag(jalr_flag)
    );

    // Register file
    wire [31:0] rs1_data;
    wire [31:0] rs2_data;
    wire [31:0] rd_wdata;

    regfile REGFILE (
        .clk(clk),
        .rst(rst),
        .we(reg_write),
        .waddr(rd_addr),
        .wdata(rd_wdata),
        .raddr1(rs1_addr),
        .raddr2(rs2_addr),
        .rdata1(rs1_data),
        .rdata2(rs2_data)
    );

    // Immediate generation
    wire [31:0] imm_i, imm_s, imm_b, imm_u, imm_j;
    imm_gen IMMGEN (
        .instr(instruction),
        .imm_i(imm_i),
        .imm_s(imm_s),
        .imm_b(imm_b),
        .imm_u(imm_u),
        .imm_j(imm_j)
    );

    // ALU inputs and operation
    wire [31:0] alu_in0 = rs1_data;

    wire [31:0] chosen_imm =
        (lui_flag)   ? imm_u :
        (jal_flag)   ? imm_j :
        (mem_write)  ? imm_s :
        (jalr_flag)  ? imm_i :
                       imm_i;

    wire [31:0] alu_in1 = alu_src ? chosen_imm : rs2_data;

    wire [31:0] alu_result;
    wire        zero_flag;
    wire        lt_signed;
    wire        lt_unsigned;

    alu ALU (
        .in0(alu_in0),
        .in1(alu_in1),
        .alu_op(alu_op),
        .result(alu_result),
        .zero(zero_flag),
        .lt_signed(lt_signed),
        .lt_unsigned(lt_unsigned)
    );

    // Data memory
    wire [31:0] mem_read_data;
    dmem DATAMEM (
        .clk(clk),
        .rst(rst),
        .addr(alu_result),
        .write_data(rs2_data),
        .mem_read(mem_read),
        .mem_write(mem_write),
        .read_data(mem_read_data)
    );

    // Branch and jump decison
    wire branch_taken = branch ? evaluate_branch(branch_type, zero_flag, lt_signed, lt_unsigned) : 1'b0;

    wire [31:0] target_pc =
        (jal_flag)     ? (pc_aligned + imm_j) :
        (jalr_flag)    ? ((rs1_data + imm_i) & ~32'd1) :
        (branch_taken) ? (pc_aligned + imm_b) :
                         pc_aligned;

    wire take_jump_or_branch = jal_flag | jalr_flag | branch_taken;

    // Writeback selection
    wire [31:0] wb_from_alu   = alu_result;
    wire [31:0] wb_from_mem   = mem_read_data;
    wire [31:0] wb_from_pc4   = PC_plus_4;
    wire [31:0] wb_from_uimm  = imm_u;
    wire [31:0] wb_from_auipc = pc_aligned + imm_u;

    reg [31:0] wb_mux_out;
    always @(*) begin
        case (wb_sel)
            2'b00: wb_mux_out = wb_from_alu;
            2'b01: wb_mux_out = wb_from_mem;
            2'b10: wb_mux_out = wb_from_pc4;
            2'b11: wb_mux_out = auipc_flag ? wb_from_auipc : wb_from_uimm;
            default: wb_mux_out = 32'hDEADBEEF;
        endcase
    end
    assign rd_wdata = wb_mux_out;

    // Sequential PC update
    always @(posedge clk or posedge rst) begin
        if (rst) begin
            PC <= 32'd0;
        end else begin
            if (take_jump_or_branch) begin
                PC <= target_pc;
            end else begin
                PC <= PC_plus_4;
            end
        end
    end

    // Branch evaluation
    function evaluate_branch;
        input [2:0] brt;
        input       z;
        input       lt_s;
        input       lt_u;
        begin
            case (brt)
                3'b000: evaluate_branch = z;
                3'b001: evaluate_branch = ~z;
                3'b100: evaluate_branch = lt_s;
                3'b101: evaluate_branch = ~lt_s;
                3'b110: evaluate_branch = lt_u;
                3'b111: evaluate_branch = ~lt_u;
                default: evaluate_branch = 1'b0;
            endcase
        end
    endfunction

endmodule

module fetch_imem (
    input  wire [7:0] addr_word,
    output reg  [31:0] instruction
);
    reg [31:0] mem [0:255];
    integer i;
    initial begin
        for (i = 27; i < 256; i = i + 1) mem[i] = 32'h00000013;
    end

    always @(*) begin
        instruction = mem[addr_word];
    end
endmodule


module imm_gen (
    input  wire [31:0] instr,
    output reg  [31:0] imm_i,
    output reg  [31:0] imm_s,
    output reg  [31:0] imm_b,
    output reg  [31:0] imm_u,
    output reg  [31:0] imm_j
);
    always @(*) begin
        imm_i = {{20{instr[31]}}, instr[31:20]};
        imm_s = {{20{instr[31]}}, instr[31:25], instr[11:7]};
        imm_b = {{19{instr[31]}}, instr[31], instr[7], instr[30:25], instr[11:8], 1'b0};
        imm_u = {instr[31:12], 12'b0};
        imm_j = {{11{instr[31]}}, instr[31], instr[19:12], instr[20], instr[30:21], 1'b0};
    end
endmodule


module decoder (
    input  wire [6:0] opcode,
    input  wire [2:0] funct3,
    input  wire [6:0] funct7,
    output reg       reg_write,
    output reg       alu_src,
    output reg [3:0] alu_op,
    output reg       mem_read,
    output reg       mem_write,
    output reg [1:0] wb_sel,
    output reg       branch,
    output reg [2:0] branch_type,
    output reg       auipc_flag,
    output reg       lui_flag,
    output reg       jal_flag,
    output reg       jalr_flag
);
    localparam ALU_ADD  = 4'd0;
    localparam ALU_SUB  = 4'd1;
    localparam ALU_AND  = 4'd2;
    localparam ALU_OR   = 4'd3;
    localparam ALU_XOR  = 4'd4;
    localparam ALU_SLL  = 4'd5;
    localparam ALU_SRL  = 4'd6;
    localparam ALU_SRA  = 4'd7;
    localparam ALU_SLT  = 4'd8;
    localparam ALU_SLTU = 4'd9;

    always @(*) begin
        reg_write   = 1'b0;
        alu_src     = 1'b0;
        alu_op      = ALU_ADD;
        mem_read    = 1'b0;
        mem_write   = 1'b0;
        wb_sel      = 2'b00;
        branch      = 1'b0;
        branch_type = 3'b000;
        auipc_flag  = 1'b0;
        lui_flag    = 1'b0;
        jal_flag    = 1'b0;
        jalr_flag   = 1'b0;

        case (opcode)
            7'b0110011: begin // R-type
                reg_write = 1'b1;
                alu_src = 1'b0;
                wb_sel = 2'b00;
                case (funct3)
                    3'b000: alu_op = (funct7 == 7'b0100000) ? ALU_SUB : ALU_ADD;
                    3'b111: alu_op = ALU_AND;
                    3'b110: alu_op = ALU_OR;
                    3'b100: alu_op = ALU_XOR;
                    3'b001: alu_op = ALU_SLL;
                    3'b101: alu_op = (funct7 == 7'b0100000) ? ALU_SRA : ALU_SRL;
                    3'b010: alu_op = ALU_SLT;
                    3'b011: alu_op = ALU_SLTU;
                    default: alu_op = ALU_ADD;
                endcase
            end

            7'b0010011: begin // OP-IMM
                reg_write = 1'b1;
                alu_src = 1'b1;
                wb_sel = 2'b00;
                case (funct3)
                    3'b000: alu_op = ALU_ADD;
                    3'b111: alu_op = ALU_AND;
                    3'b110: alu_op = ALU_OR;
                    3'b100: alu_op = ALU_XOR;
                    3'b001: alu_op = ALU_SLL;
                    3'b101: alu_op = (funct7[5] == 1'b1) ? ALU_SRA : ALU_SRL;
                    3'b010: alu_op = ALU_SLT;
                    3'b011: alu_op = ALU_SLTU;
                    default: alu_op = ALU_ADD;
                endcase
            end

            7'b0000011: begin // LOAD
                reg_write = 1'b1;
                alu_src = 1'b1;
                alu_op = ALU_ADD;
                mem_read = 1'b1;
                wb_sel = 2'b01;
            end

            7'b0100011: begin // STORE
                reg_write = 1'b0;
                alu_src = 1'b1;
                alu_op = ALU_ADD;
                mem_write = 1'b1;
                wb_sel = 2'b00;
            end

            7'b1100011: begin // BRANCH
                reg_write = 1'b0;
                alu_src = 1'b0;
                branch = 1'b1;
                branch_type = funct3;
                case (funct3)
                    3'b000: alu_op = ALU_SUB;
                    3'b001: alu_op = ALU_SUB;
                    3'b100: alu_op = ALU_SLT;
                    3'b101: alu_op = ALU_SLT;
                    3'b110: alu_op = ALU_SLTU;
                    3'b111: alu_op = ALU_SLTU;
                    default: alu_op = ALU_SUB;
                endcase
            end

            7'b0110111: begin // LUI
                reg_write = 1'b1;
                alu_src = 1'b1;
                wb_sel = 2'b11;
                lui_flag = 1'b1;
            end

            7'b0010111: begin // AUIPC
                reg_write = 1'b1;
                wb_sel = 2'b11;
                auipc_flag = 1'b1;
            end

            7'b1101111: begin // JAL
                reg_write = 1'b1;
                wb_sel = 2'b10;
                jal_flag = 1'b1;
            end

            7'b1100111: begin // JALR
                reg_write = 1'b1;
                alu_src = 1'b1;
                alu_op = ALU_ADD;
                wb_sel = 2'b10;
                jalr_flag = 1'b1;
            end

            default: begin
            end
        endcase
    end
endmodule


module alu (
    input  wire [31:0] in0,
    input  wire [31:0] in1,
    input  wire [3:0]  alu_op,
    output reg  [31:0] result,
    output reg         zero,
    output reg         lt_signed,
    output reg         lt_unsigned
);
    always @(*) begin
        case (alu_op)
            4'd0: result = in0 + in1;
            4'd1: result = in0 - in1;
            4'd2: result = in0 & in1;
            4'd3: result = in0 | in1;
            4'd4: result = in0 ^ in1;
            4'd5: result = in0 << in1[4:0];
            4'd6: result = in0 >> in1[4:0];
            4'd7: result = $signed(in0) >>> in1[4:0];
            4'd8: result = ($signed(in0) < $signed(in1)) ? 32'd1 : 32'd0;
            4'd9: result = (in0 < in1) ? 32'd1 : 32'd0;
            default: result = 32'd0;
        endcase

        zero = (result == 32'd0);
        lt_signed = ($signed(in0) < $signed(in1)) ? 1'b1 : 1'b0;
        lt_unsigned = (in0 < in1) ? 1'b1 : 1'b0;
    end
endmodule


module regfile (
    input  wire clk,
    input  wire rst,
    input  wire we,
    input  wire [4:0] waddr,
    input  wire [31:0] wdata,
    input  wire [4:0] raddr1,
    input  wire [4:0] raddr2,
    output reg  [31:0] rdata1,
    output reg  [31:0] rdata2
);
    reg [31:0] regs [0:31];
    integer i;

    always @(posedge clk or posedge rst) begin
        if (rst) begin
            for (i = 0; i < 32; i = i + 1) regs[i] <= 32'd0;
        end else begin
            if (we && (waddr != 5'd0)) regs[waddr] <= wdata;
            regs[0] <= 32'd0;
        end
    end

    always @(*) begin
        rdata1 = (raddr1 == 5'd0) ? 32'd0 : regs[raddr1];
        rdata2 = (raddr2 == 5'd0) ? 32'd0 : regs[raddr2];
    end
endmodule


module dmem (
    input  wire        clk,
    input  wire        rst,
    input  wire [31:0] addr,
    input  wire [31:0] write_data,
    input  wire        mem_read,
    input  wire        mem_write,
    output reg  [31:0] read_data
);
    reg [31:0] data_mem [0:1023];
    integer i;
    initial begin
        for (i = 0; i < 1024; i = i + 1) data_mem[i] = 32'd0;
        read_data = 32'd0;
    end

    always @(posedge clk) begin
        if (mem_write) begin
            data_mem[addr[11:2]] <= write_data;
        end
    end
    
    always @(*) begin
        if (mem_read)  read_data = data_mem[addr[11:2]];
        else           read_data = 32'd0;
    end
endmodule

tb/tb_cpu_top.v
`timescale 1ns/1ps
`include "rtl/cpu_top.v"

module tb_cpu_top;

    reg clk;
    reg rst;

    cpu_top uut (
        .clk(clk),
        .rst(rst)
    );

    initial begin
        clk = 0;
        forever #5 clk = ~clk;
    end

    initial begin
        $dumpfile("cpu_waveform.vcd");
        $dumpvars(0, tb_cpu_top);
    end

    initial begin

        rst = 1;
        #20;

        rst = 0;

        uut.IMEM.mem[0]  = 32'h00A00093;  // addi x1, x0, 10
        uut.IMEM.mem[1]  = 32'h00300113;  // addi x2, x0, 3
        uut.IMEM.mem[2]  = 32'hFFB00193;  // addi x3, x0, -5
        uut.IMEM.mem[3]  = 32'h00200213;  // addi x4, x0, 2

        uut.IMEM.mem[4]  = 32'h002082B3;  // add  x5, x1, x2
        uut.IMEM.mem[5]  = 32'h40208333;  // sub  x6, x1, x2
        uut.IMEM.mem[6]  = 32'h0020F3B3;  // and  x7, x1, x2
        uut.IMEM.mem[7]  = 32'h0020E433;  // or   x8, x1, x2
        uut.IMEM.mem[8]  = 32'h0020C4B3;  // xor  x9, x1, x2
        uut.IMEM.mem[9]  = 32'h00112533;  // slt  x10, x2, x1
        uut.IMEM.mem[10] = 32'h0011B5B3;  // sltu x11, x3, x1
        uut.IMEM.mem[11] = 32'h00409633;  // sll  x12, x1, x4
        uut.IMEM.mem[12] = 32'h0040D6B3;  // srl  x13, x1, x4
        uut.IMEM.mem[13] = 32'h4041D733;  // sra  x14, x3, x4

        #3000;

        rst = 1;
        #20;
        $finish;
    end
endmodule

cpu_waveform.vcd
$date
	Fri Mar 13 15:08:24 2026
$end
$version
	Icarus Verilog
$end
$timescale
	1ps
$end
$scope module tb_cpu_top $end
$var reg 1 ! clk $end
$var reg 1 " rst $end
$scope module uut $end
$var wire 32 # alu_in0 [31:0] $end
$var wire 1 ! clk $end
$var wire 32 $ pc_arch [31:0] $end
$var wire 32 % rd_wdata [31:0] $end
$var wire 1 " rst $end
$var wire 1 & take_jump_or_branch $end
$var wire 32 ' wb_from_alu [31:0] $end
$var wire 32 ( wb_from_mem [31:0] $end
$var wire 32 ) wb_from_pc4 [31:0] $end
$var wire 32 * wb_from_uimm [31:0] $end
$var wire 1 + zero_flag $end
$var wire 2 , wb_sel [1:0] $end
$var wire 32 - wb_from_auipc [31:0] $end
$var wire 32 . target_pc [31:0] $end
$var wire 32 / rs2_data [31:0] $end
$var wire 5 0 rs2_addr [4:0] $end
$var wire 32 1 rs1_data [31:0] $end
$var wire 5 2 rs1_addr [4:0] $end
$var wire 1 3 reg_write $end
$var wire 5 4 rd_addr [4:0] $end
$var wire 32 5 pc_aligned [31:0] $end
$var wire 7 6 opcode [6:0] $end
$var wire 1 7 mem_write $end
$var wire 32 8 mem_read_data [31:0] $end
$var wire 1 9 mem_read $end
$var wire 1 : lui_flag $end
$var wire 1 ; lt_unsigned $end
$var wire 1 < lt_signed $end
$var wire 1 = jalr_flag $end
$var wire 1 > jal_flag $end
$var wire 32 ? instruction [31:0] $end
$var wire 32 @ imm_u [31:0] $end
$var wire 32 A imm_s [31:0] $end
$var wire 32 B imm_j [31:0] $end
$var wire 32 C imm_i [31:0] $end
$var wire 32 D imm_b [31:0] $end
$var wire 7 E funct7 [6:0] $end
$var wire 3 F funct3 [2:0] $end
$var wire 32 G chosen_imm [31:0] $end
$var wire 3 H branch_type [2:0] $end
$var wire 1 I branch_taken $end
$var wire 1 J branch $end
$var wire 1 K auipc_flag $end
$var wire 1 L alu_src $end
$var wire 32 M alu_result [31:0] $end
$var wire 4 N alu_op [3:0] $end
$var wire 32 O alu_in1 [31:0] $end
$var wire 32 P PC_plus_4 [31:0] $end
$var reg 32 Q PC [31:0] $end
$var reg 32 R wb_mux_out [31:0] $end
$scope function evaluate_branch $end
$var reg 3 S brt [2:0] $end
$var reg 1 T lt_s $end
$var reg 1 U lt_u $end
$var reg 1 V z $end
$upscope $end
$scope module ALU $end
$var wire 32 W in0 [31:0] $end
$var wire 32 X in1 [31:0] $end
$var wire 4 Y alu_op [3:0] $end
$var reg 1 < lt_signed $end
$var reg 1 ; lt_unsigned $end
$var reg 32 Z result [31:0] $end
$var reg 1 + zero $end
$upscope $end
$scope module DATAMEM $end
$var wire 32 [ addr [31:0] $end
$var wire 1 ! clk $end
$var wire 1 " rst $end
$var wire 32 \ write_data [31:0] $end
$var wire 1 7 mem_write $end
$var wire 1 9 mem_read $end
$var reg 32 ] read_data [31:0] $end
$var integer 32 ^ i [31:0] $end
$upscope $end
$scope module DEC $end
$var wire 3 _ funct3 [2:0] $end
$var wire 7 ` funct7 [6:0] $end
$var wire 7 a opcode [6:0] $end
$var parameter 4 b ALU_ADD $end
$var parameter 4 c ALU_AND $end
$var parameter 4 d ALU_OR $end
$var parameter 4 e ALU_SLL $end
$var parameter 4 f ALU_SLT $end
$var parameter 4 g ALU_SLTU $end
$var parameter 4 h ALU_SRA $end
$var parameter 4 i ALU_SRL $end
$var parameter 4 j ALU_SUB $end
$var parameter 4 k ALU_XOR $end
$var reg 4 l alu_op [3:0] $end
$var reg 1 L alu_src $end
$var reg 1 K auipc_flag $end
$var reg 1 J branch $end
$var reg 3 m branch_type [2:0] $end
$var reg 1 > jal_flag $end
$var reg 1 = jalr_flag $end
$var reg 1 : lui_flag $end
$var reg 1 9 mem_read $end
$var reg 1 7 mem_write $end
$var reg 1 3 reg_write $end
$var reg 2 n wb_sel [1:0] $end
$upscope $end
$scope module IMEM $end
$var wire 8 o addr_word [7:0] $end
$var reg 32 p instruction [31:0] $end
$var integer 32 q i [31:0] $end
$upscope $end
$scope module IMMGEN $end
$var wire 32 r instr [31:0] $end
$var reg 32 s imm_b [31:0] $end
$var reg 32 t imm_i [31:0] $end
$var reg 32 u imm_j [31:0] $end
$var reg 32 v imm_s [31:0] $end
$var reg 32 w imm_u [31:0] $end
$upscope $end
$scope module REGFILE $end
$var wire 1 ! clk $end
$var wire 5 x raddr1 [4:0] $end
$var wire 5 y raddr2 [4:0] $end
$var wire 1 " rst $end
$var wire 5 z waddr [4:0] $end
$var wire 32 { wdata [31:0] $end
$var wire 1 3 we $end
$var reg 32 | rdata1 [31:0] $end
$var reg 32 } rdata2 [31:0] $end
$var integer 32 ~ i [31:0] $end
$upscope $end
$upscope $end
$upscope $end
$enddefinitions $end
$comment Show the parameter values. $end
$dumpall
b100 k
b1 j
b110 i
b111 h
b1001 g
b1000 f
b101 e
b11 d
b10 c
b0 b
$end
#0
$dumpvars
b100000 ~
b0 }
b0 |
b1010 {
b1 z
b1010 y
b0 x
b101000000000000000000000 w
b1 v
b1010 u
b1010 t
b100000000000 s
b101000000000000010010011 r
b100000000 q
b101000000000000010010011 p
b0 o
b0 n
b0 m
b0 l
b10011 a
b0 `
b0 _
b10000000000 ^
b0 ]
b0 \
b1010 [
b1010 Z
b0 Y
b1010 X
b0 W
0V
1U
1T
b0 S
b1010 R
b0 Q
b100 P
b1010 O
b0 N
b1010 M
1L
0K
0J
0I
b0 H
b1010 G
b0 F
b0 E
b100000000000 D
b1010 C
b1010 B
b1 A
b101000000000000000000000 @
b101000000000000010010011 ?
0>
0=
1<
1;
0:
09
b0 8
07
b10011 6
b0 5
b1 4
13
b0 2
b0 1
b1010 0
b0 /
b0 .
b101000000000000000000000 -
b0 ,
0+
b101000000000000000000000 *
b100 )
b0 (
b1010 '
0&
b1010 %
b0 $
b0 #
1"
0!
$end
#5000
b100000 ~
1!
#10000
0!
#15000
b100000 ~
1!
#20000
0!
0"
#25000
b11 %
b11 {
b11 R
b11 '
b11 M
b11 Z
b11 [
b11 O
b11 X
b11 G
b100 .
b100000000010 B
b100000000010 u
b1100000000000000000000 *
b1100000000000000000000 @
b1100000000000000000000 w
b10 D
b10 s
b10 A
b10 v
b11 C
b11 t
b11 0
b11 y
b10 4
b10 z
b1100000000000100010011 ?
b1100000000000100010011 p
b1100000000000100010011 r
b1 o
b1100000000000000000100 -
b100 5
b1000 )
b1000 P
b100 $
b100 Q
1!
#30000
0!
#35000
0T
b11111111111111111111111111111011 %
b11111111111111111111111111111011 {
b11111111111111111111111111111011 R
0<
b11111111111111111111111111111011 '
b11111111111111111111111111111011 M
b11111111111111111111111111111011 Z
b11111111111111111111111111111011 [
b11111111111111111111111111111011 O
b11111111111111111111111111111011 X
b11111111111111111111111111111011 G
1L
13
b1000 .
b11111111111100000000111111111010 B
b11111111111100000000111111111010 u
b11111111101100000000000000000000 *
b11111111101100000000000000000000 @
b11111111101100000000000000000000 w
b11111111111111111111111111100010 D
b11111111111111111111111111100010 s
b11111111111111111111111111100011 A
b11111111111111111111111111100011 v
b11111111111111111111111111111011 C
b11111111111111111111111111111011 t
b11011 0
b11011 y
b11 4
b11 z
b1111111 E
b1111111 `
b11111111101100000000000110010011 ?
b11111111101100000000000110010011 p
b11111111101100000000000110010011 r
b10 o
b11111111101100000000000000001000 -
b1000 5
b1100 )
b1100 P
b1000 $
b1000 Q
1!
#40000
0!
#45000
1T
b10 %
b10 {
b10 R
1<
b10 '
b10 M
b10 Z
b10 [
b10 O
b10 X
b10 G
b11 /
b11 \
b11 }
1L
13
b1100 .
b10 B
b10 u
b1000000000000000000000 *
b1000000000000000000000 @
b1000000000000000000000 w
b100 D
b100 s
b100 A
b100 v
b10 C
b10 t
b10 0
b10 y
b100 4
b100 z
b0 E
b0 `
b1000000000001000010011 ?
b1000000000001000010011 p
b1000000000001000010011 r
b11 o
b1000000000000000001100 -
b1100 5
b10000 )
b10000 P
b1100 $
b1100 Q
1!
#50000
0!
#55000
0U
0T
b1101 %
b1101 {
b1101 R
0;
0<
b1101 '
b1101 M
b1101 Z
b1101 [
b11 O
b11 X
b1010 #
b1010 W
b1010 1
b1010 |
0L
13
b10000 .
b1000000000000010 B
b1000000000000010 u
b1000001000000000000000 *
b1000001000000000000000 @
b1000001000000000000000 w
b100000000100 D
b100000000100 s
b101 A
b101 v
b1 2
b1 x
b101 4
b101 z
b110011 6
b110011 a
b1000001000001010110011 ?
b1000001000001010110011 p
b1000001000001010110011 r
b100 o
b1000001000000000010000 -
b10000 5
b10100 )
b10100 P
b10000 $
b10000 Q
1!
#60000
0!
#65000
b10000000010 G
b111 %
b111 {
b111 R
b111 '
b111 M
b111 Z
b111 [
b1 N
b1 Y
b1 l
13
b10100 .
b1000010000000010 B
b1000010000000010 u
b1000000001000001000000000000000 *
b1000000001000001000000000000000 @
b1000000001000001000000000000000 w
b10000000110 D
b10000000110 s
b10000000110 A
b10000000110 v
b10000000010 C
b10000000010 t
b110 4
b110 z
b100000 E
b100000 `
b1000000001000001000001100110011 ?
b1000000001000001000001100110011 p
b1000000001000001000001100110011 r
b101 o
b1000000001000001000000000010100 -
b10100 5
b11000 )
b11000 P
b10100 $
b10100 Q
1!
#70000
0!
#75000
b10 G
b10 %
b10 {
b10 R
b10 '
b10 M
b10 Z
b10 [
b10 N
b10 Y
b10 l
13
b11000 .
b1111000000000010 B
b1111000000000010 u
b1000001111000000000000 *
b1000001111000000000000 @
b1000001111000000000000 w
b100000000110 D
b100000000110 s
b111 A
b111 v
b10 C
b10 t
b111 4
b111 z
b0 E
b0 `
b111 F
b111 _
b1000001111001110110011 ?
b1000001111001110110011 p
b1000001111001110110011 r
b110 o
b1000001111000000011000 -
b11000 5
b11100 )
b11100 P
b11000 $
b11000 Q
1!
#80000
0!
#85000
b1011 %
b1011 {
b1011 R
b1011 '
b1011 M
b1011 Z
b1011 [
b11 N
b11 Y
b11 l
13
b11100 .
b1110000000000010 B
b1110000000000010 u
b1000001110000000000000 *
b1000001110000000000000 @
b1000001110000000000000 w
b1000 D
b1000 s
b1000 A
b1000 v
b1000 4
b1000 z
b110 F
b110 _
b1000001110010000110011 ?
b1000001110010000110011 p
b1000001110010000110011 r
b111 o
b1000001110000000011100 -
b11100 5
b100000 )
b100000 P
b11100 $
b11100 Q
1!
#90000
0!
#95000
b1001 %
b1001 {
b1001 R
b1001 '
b1001 M
b1001 Z
b1001 [
b100 N
b100 Y
b100 l
13
b100000 .
b1100000000000010 B
b1100000000000010 u
b1000001100000000000000 *
b1000001100000000000000 @
b1000001100000000000000 w
b100000001000 D
b100000001000 s
b1001 A
b1001 v
b1001 4
b1001 z
b100 F
b100 _
b1000001100010010110011 ?
b1000001100010010110011 p
b1000001100010010110011 r
b1000 o
b1000001100000000100000 -
b100000 5
b100100 )
b100100 P
b100000 $
b100000 Q
1!
#100000
0!
#105000
b1 G
1U
1T
1;
1<
0V
b1 %
b1 {
b1 R
b1010 O
b1010 X
0+
b1 '
b1 M
b1 Z
b1 [
b1010 /
b1010 \
b1010 }
b11 #
b11 W
b11 1
b11 |
b1000 N
b1000 Y
b1000 l
13
b100100 .
b10010100000000000 B
b10010100000000000 u
b100010010000000000000 *
b100010010000000000000 @
b100010010000000000000 w
b1010 D
b1010 s
b1010 A
b1010 v
b1 C
b1 t
b1 0
b1 y
b10 2
b10 x
b1010 4
b1010 z
b10 F
b10 _
b100010010010100110011 ?
b100010010010100110011 p
b100010010010100110011 r
b1001 o
b100010010000000100100 -
b100100 5
b101000 )
b101000 P
b100100 $
b100100 Q
1!
#110000
0!
#115000
0U
1V
b0 %
b0 {
b0 R
0;
1+
b0 '
b0 M
b0 Z
b0 [
b11111111111111111111111111111011 #
b11111111111111111111111111111011 W
b11111111111111111111111111111011 1
b11111111111111111111111111111011 |
b1001 N
b1001 Y
b1001 l
13
b101000 .
b11011100000000000 B
b11011100000000000 u
b100011011000000000000 *
b100011011000000000000 @
b100011011000000000000 w
b100000001010 D
b100000001010 s
b1011 A
b1011 v
b11 2
b11 x
b1011 4
b1011 z
b11 F
b11 _
b100011011010110110011 ?
b100011011010110110011 p
b100011011010110110011 r
b1010 o
b100011011000000101000 -
b101000 5
b101100 )
b101100 P
b101000 $
b101000 Q
1!
#120000
0!
#125000
b100 G
0T
0V
b101000 %
b101000 {
b101000 R
b10 O
b10 X
0<
0+
b101000 '
b101000 M
b101000 Z
b101000 [
b10 /
b10 \
b10 }
b1010 #
b1010 W
b1010 1
b1010 |
b101 N
b101 Y
b101 l
13
b101100 .
b1001000000000100 B
b1001000000000100 u
b10000001001000000000000 *
b10000001001000000000000 @
b10000001001000000000000 w
b1100 D
b1100 s
b1100 A
b1100 v
b100 C
b100 t
b100 0
b100 y
b1 2
b1 x
b1100 4
b1100 z
b1 F
b1 _
b10000001001011000110011 ?
b10000001001011000110011 p
b10000001001011000110011 r
b1011 o
b10000001001000000101100 -
b101100 5
b110000 )
b110000 P
b101100 $
b101100 Q
1!
#130000
0!
#135000
b10 %
b10 {
b10 R
b10 '
b10 M
b10 Z
b10 [
b110 N
b110 Y
b110 l
13
b110000 .
b1101000000000100 B
b1101000000000100 u
b10000001101000000000000 *
b10000001101000000000000 @
b10000001101000000000000 w
b100000001100 D
b100000001100 s
b1101 A
b1101 v
b1101 4
b1101 z
b101 F
b101 _
b10000001101011010110011 ?
b10000001101011010110011 p
b10000001101011010110011 r
b1100 o
b10000001101000000110000 -
b110000 5
b110100 )
b110100 P
b110000 $
b110000 Q
1!
#140000
0!
#145000
b10000000100 G
1T
b11111111111111111111111111111110 %
b11111111111111111111111111111110 {
b11111111111111111111111111111110 R
1<
b11111111111111111111111111111110 '
b11111111111111111111111111111110 M
b11111111111111111111111111111110 Z
b11111111111111111111111111111110 [
b11111111111111111111111111111011 #
b11111111111111111111111111111011 W
b11111111111111111111111111111011 1
b11111111111111111111111111111011 |
b111 N
b111 Y
b111 l
13
b110100 .
b11101010000000100 B
b11101010000000100 u
b1000000010000011101000000000000 *
b1000000010000011101000000000000 @
b1000000010000011101000000000000 w
b10000001110 D
b10000001110 s
b10000001110 A
b10000001110 v
b10000000100 C
b10000000100 t
b11 2
b11 x
b1110 4
b1110 z
b100000 E
b100000 `
b1000000010000011101011100110011 ?
b1000000010000011101011100110011 p
b1000000010000011101011100110011 r
b1101 o
b1000000010000011101000000110100 -
b110100 5
b111000 )
b111000 P
b110100 $
b110100 Q
1!
#150000
0!
#155000
0T
1V
0<
1+
b0 G
0U
b0 %
b0 {
b0 R
b0 O
b0 X
0;
b0 '
b0 M
b0 Z
b0 [
b1101 /
b1101 \
b1101 }
b0 #
b0 W
b0 1
b0 |
17
1L
b0 N
b0 Y
b0 l
03
b111000 .
b10100000000100 B
b10100000000100 u
b10100000010000000000000 *
b10100000010000000000000 @
b10100000010000000000000 w
b0 D
b0 s
b0 A
b0 v
b101 C
b101 t
b101 0
b101 y
b0 2
b0 x
b0 4
b0 z
b0 E
b0 `
b10 F
b10 _
b100011 6
b100011 a
b10100000010000000100011 ?
b10100000010000000100011 p
b10100000010000000100011 r
b1110 o
b10100000010000000111000 -
b111000 5
b111100 )
b111100 P
b111000 $
b111000 Q
1!
#160000
0!
#165000
b1101 %
b1101 {
b1101 R
b1101 (
b1101 8
b1101 ]
b0 /
b0 \
b0 }
b1 ,
b1 n
19
13
07
1L
b111100 .
b10000000000000 B
b10000000000000 u
b10000000000000 *
b10000000000000 @
b10000000000000 w
b100000001110 D
b100000001110 s
b1111 A
b1111 v
b0 C
b0 t
b0 0
b0 y
b1111 4
b1111 z
b11 6
b11 a
b10011110000011 ?
b10011110000011 p
b10011110000011 r
b1111 o
b10000000111100 -
b111100 5
b1000000 )
b1000000 P
b111100 $
b111100 Q
1!
#170000
0!
